generatepdfs/__init__.py
generatepdfs/generate_pdfs.py
generatepdfs/pdf.py
generatepdfs/exceptions/__init__.py
generatepdfs/exceptions/invalid_argument_exception.py
generatepdfs/exceptions/runtime_exception.py
generatepdfs_python_sdk-1.0.0.dist-info/licenses/LICENSE
generatepdfs_python_sdk-1.0.0.dist-info/METADATA
generatepdfs_python_sdk-1.0.0.dist-info/WHEEL
generatepdfs_python_sdk-1.0.0.dist-info/top_level.txt
generatepdfs_python_sdk-1.0.0.dist-info/RECORD
