Metadata-Version: 2.4
Name: generatepdfs-python-sdk
Version: 1.0.0
Summary: Python SDK for GeneratePDFs.com API
Home-page: https://github.com/GeneratePDFs/python-sdk
Author: GeneratePDFs
License: MIT
Project-URL: Homepage, https://github.com/GeneratePDFs/python-sdk
Project-URL: Documentation, https://github.com/GeneratePDFs/python-sdk
Project-URL: Repository, https://github.com/GeneratePDFs/python-sdk
Project-URL: Issues, https://github.com/GeneratePDFs/python-sdk/issues
Keywords: pdf,generate,api,sdk,python
Classifier: Development Status :: 4 - Beta
Classifier: Intended Audience :: Developers
Classifier: License :: OSI Approved :: MIT License
Classifier: Programming Language :: Python :: 3
Classifier: Programming Language :: Python :: 3.8
Classifier: Programming Language :: Python :: 3.9
Classifier: Programming Language :: Python :: 3.10
Classifier: Programming Language :: Python :: 3.11
Classifier: Programming Language :: Python :: 3.12
Classifier: Topic :: Software Development :: Libraries :: Python Modules
Requires-Python: >=3.8
License-File: LICENSE
Requires-Dist: requests>=2.28.0
Provides-Extra: dev
Requires-Dist: pytest>=7.0.0; extra == "dev"
Requires-Dist: pytest-cov>=4.0.0; extra == "dev"
Requires-Dist: black>=23.0.0; extra == "dev"
Requires-Dist: mypy>=1.0.0; extra == "dev"
Requires-Dist: ruff>=0.1.0; extra == "dev"
Dynamic: home-page
Dynamic: license-file
Dynamic: requires-python
